<?xml version="1.0"?>
<?xml-stylesheet type="text/xsl" href="stand.xsl"?>
<PAGE xml:space="preserve">
<NAV_HEADER>
<PREV>WR-04-16_n0279.xml</PREV>
<NEXT>WR-04-16_n0281.xml</NEXT>
<UP></UP>
<DISP>Wiener Rundschau: Jg. 4, Nr. 16, S. 280</DISP>
<DOC_CHAR_NUM></DOC_CHAR_NUM>
<FOLDER_DOCS>552</FOLDER_DOCS>
<FOLDER_DOCS_RN></FOLDER_DOCS_RN>
<ISSUE_DOCS>16</ISSUE_DOCS>
<PUBL_DATE><PUBL_DAY></PUBL_DAY><PUBL_MONTH></PUBL_MONTH><PUBL_YEAR>1900</PUBL_YEAR></PUBL_DATE>
<NEXT_START/>
<TEXT_START/>
<ISSUE_PN></ISSUE_PN>
</NAV_HEADER>
<HD><CTEXT>PANIZZA: DER <LANG iso="fr"><DATE>QUATORZE JUILLET</DATE></LANG>.</CTEXT></HD>
<TABLE parID="03458"><ROW ciID="0662"><CELL>
<P part="final" parID="03459">Tisch und gesticuliert? Das Gedr&#xE4;nge wird<LE/>
furchtbar. Einige Menschen sind in die<LE/>
Bassins gefallen. Nein! es ist die Strafe<LE/>
f&#xFC;r Diejenigen, die sich unterstanden haben,<LE/>
gegen die Sache des Volkes zu sprechen<LE/>
und zu sagen: das K&#xF6;nigthum sei die<LE/>
Ordnung. Man zieht sie heraus; alles lacht<LE/>
f&#xFC;rchterlich. Sie sind ganz nass. Man<LE/>
haut sie durch <SYMBOL type="4dots"/>* Was ist dort? Ein<LE/>
Mensch auf den Knien. Man hat ihn<LE/>
geschlagen. Man hat ihn hinten geschlagen<LE/>
und mit F&#xFC;&#xDF;en getreten. Jetzt h&#xF6;ren sie<LE/>
auf. Er senkt das Gesicht zu Boden und<LE/>
k&#xFC;sst den Garten <SYMBOL type="6dots"/> Was ist? Es<LE/>
ist eine Ceremonie; er k&#xFC;sst den Boden<LE/>
Frankreichs; es ist wieder eine Strafe<LE/>
f&#xFC;r einen Vorlauten. Er hat dummes Zeug<LE/>
gesagt. Er hat antirevolution&#xE4;res Zeug<LE/>
geschw&#xE4;tzt <SYMBOL type="4dots"/>** Man singt! H&#xF6;ren<LE/>
Sie, man singt! <SYMBOL type="4dots"/> Ganz deutlich:<LE/>
<I>Tra-la-la-la!</I> <SYMBOL type="4dots"/> H&#xF6;ren Sie die Strophe?<LE/>
&#x2014; Man singt! &#x2014; Es kommt n&#xE4;her! &#x2014;<LE/>
Man kann es nicht h&#xF6;ren. Desmoulins<LE/>
schreit zu laut. Wir sind zu nahe an <HYPH1 cont="Desmoulins&#x2019;">Des-</HYPH1><LE/>
<HYPH2>moulins&#x2019;</HYPH2> Tisch gekommen. Die Brosch&#xFC;re<LE/>
von Desmoulins ist vergriffen. Was hat<LE/>
er gesagt? Er sagt den Leuten, was er<LE/>
ungef&#xE4;hr geschrieben hat <SYMBOL type="4dots"/> Der Gesang<LE/>
kommt n&#xE4;her: <I>Tra-la-la-la!</I> &#x2014; H&#xF6;ren Sie!<LE/>
Kennen Sie die Strophe? &#x2014; Es ist ein<LE/>
Gesang! &#x2014; Hunderte singen! &#x2014; Was<LE/>
sagt Desmoulins? Desmoulins schreit zu<LE/>
laut! &#x2014; Da ist der Gesang; sie haben<LE/>
Zweige an ihren H&#xFC;ten <SYMBOL type="5dots"/></P>
<DIV_START author="(other)" cat="song" type="verse" divStartID="dsID_2436_00724" endPtr="WR-04-16_n0280.xml#//DIV_END[@divEndID='deID_2436_00721']"/>
<LG parID="03460"><LANG iso="fr"><I><L>Allons enfants de la patrie</L>
<L>Le jour de gloire est arriv&#xE9;!</L></I></LANG></LG>
<DIV_END divEndID="deID_2436_00721" startPtr="WR-04-16_n0280.xml#//DIV_START[@divStartID='dsID_2436_00724']"/>
<P parID="03461"><TAB/>Sie marschieren. Der Mund ist bei allen<LE/>
offen. Die Halsbinden flattern. Es trampelt.<LE/>
Es schritttrampelt. Die Erde zittert <SYMBOL type="5dots"/><LE/>
Sie gehen vor&#xFC;ber <SYMBOL type="6dots"/> Man h&#xF6;rt sie<LE/>
singen:</P>
<DIV_START author="(other)" cat="song" type="verse" divStartID="dsID_2436_00725" endPtr="WR-04-16_n0280.xml#//DIV_END[@divEndID='deID_2436_00722']"/>
<LG parID="03462"><LANG iso="fr"><I><L><SYMBOL type="6dots"/> Formez vos bataillons!</L>
<L>Qu&#x2019;un sang impur abreuve nos sillons <SYMBOL type="3dots"/></L></I></LANG></LG>
<DIV_END divEndID="deID_2436_00722" startPtr="WR-04-16_n0280.xml#//DIV_START[@divStartID='dsID_2436_00725']"/>
<P part="initial" parID="03463"><TAB/>Was ist mit Desmoulins? Er gesticuliert<LE/>
noch immer. Er hat sich &#xFC;berschrien.<LE/>
Er ist ganz heiser. Er sagt ungef&#xE4;hr:<LE/>
<LANG iso="fr" part="initial">&#x201E;<I>Puisque la b&#xEA;te est dans le pi&#xE8;ge, qu&#x2019;on<LE/>
l&#x2019;assomme. Jamais plus riche proie n&#x2019;aura<LE/>
&#xE9;t&#xE9; offerte aux vainqueurs. Quarante mille<LE/>
palais, h&#xF4;tels, ch&#xE2;teaux, les deux cinqui&#xE8;mes</I></LANG></P>
</CELL><CELL>
<P part="final" parID="03464"><LANG iso="fr" part="final"><I>des biens de la France, seront le prix de<LE/>
la valeur. Ceux qui se pr&#xE9;tendent conqu&#xE9;rants<LE/>
seront conquis &#xE0; leur tour. La nation sera<LE/>
purg&#xE9;e <SYMBOL type="3dots"/></I>&#xAB;</LANG>*** Dann bricht Desmoulins<LE/>
einen Zweig von den gr&#xFC;nen <HYPH1 cont="Fr&#xFC;hlingsb&#xE4;umen">Fr&#xFC;hlings-</HYPH1><LE/>
<HYPH2>b&#xE4;umen</HYPH2> des <I>Jardin Royal</I> &#x2014; Alle brechen<LE/>
einen Zweig von den gr&#xFC;nen <HYPH1 cont="Fr&#xFC;hlingsb&#xE4;umen">Fr&#xFC;hlings-</HYPH1><LE/>
<HYPH2>b&#xE4;umen</HYPH2> des <I>Jardin Royal</I> <SYMBOL type="6dots"/></P>
<P parID="03465"><TAB/>Und dann marschiert man zur<LE/>
<SPC>Bastille</SPC> &#x2014;</P>
<P parID="03466"><TAB/>Das war der <DATE><LANG iso="fr"><I>quatorze Juillet</I></LANG> von 1789</DATE>.</P>
<SEPARATOR type="asterisk"/>
<P part="initial" parID="03467"><TAB/><I>Place de la Concorde.</I> Eine schw&#xFC;le,<LE/>
erdr&#xFC;ckende Sommerhitze schon in der<LE/>
Fr&#xFC;h um 9 Uhr. Die Candelaber des<LE/>
Riesenplatzes mit Guirlanden von <HYPH1 cont="Tausenden">Tau-</HYPH1><LE/>
<HYPH2>senden</HYPH2> von farbigen Blumen und <HYPH1 cont="elektrischen">elek-</HYPH1><LE/>
<HYPH2>trischen</HYPH2> Glasbirnen verbunden, denn am<LE/>
Abend ist Illumination durch ganz Paris.<LE/>
Auch die rothgeschm&#xFC;ckten Estraden der<LE/>
Musikcorps sieht man schon da und dort<LE/>
aufgeschlagen, denn am Abend tanzt das<LE/>
ganze Volk auf den Stra&#xDF;en und Pl&#xE4;tzen<LE/>
durch ganz Paris. Schweigend ziehen die<LE/>
zahlreichen Mitglieder der <HYPH1 cont="els&#xE4;ssisch-lothringischen">els&#xE4;ssisch-loth-</HYPH1><LE/>
<HYPH2>ringischen</HYPH2> Vereine einher, mit Fahnen<LE/>
und Standarten, mit Kr&#xE4;nzen und <HYPH1 cont="Guirlanden">Guir-</HYPH1><LE/>
<HYPH2>landen</HYPH2> <SYMBOL type="6dots"/> Tausende von Menschen.<LE/>
Ein Herr, ein Herr von einem Comit&#xE9;,<LE/>
im schwarzen Frack mit farbiger Binde,<LE/>
empf&#xE4;ngt sie und ruft den einzelnen <HYPH1 cont="Vorst&#xE4;nden">Vor-</HYPH1><LE/>
<HYPH2>st&#xE4;nden</HYPH2> der Arrondissements halblaut zu:<LE/>
Keine Reden, meine Herren, nicht wahr?<LE/>
Keine Manifestationen <SYMBOL type="4dots"/> <LANG iso="fr"><I>Pas de discours,<LE/>
n&#x2019;est-ce pas, Messieurs?</I></LANG> <SYMBOL type="3dots"/> Man gibt den<LE/>
Ruf weiter: <LANG iso="fr"><I>Pas de discours!</I></LANG> Keine Reden!<LE/>
In der Ferne stehen Tausende von <LANG iso="fr"><I>Sergents<LE/>
de ville</I></LANG> und beobachten schweigend die<LE/>
Ceremonien. Niemand, der nicht Mitglied<LE/>
einer der nationalistischen Vereine ist, darf<LE/>
herantreten. Das Ziel, der Mittelpunkt all&#x2019;<LE/>
dieser Heranmaschierenden ist die Statue<LE/>
der Stadt Strassburg in der nord&#xF6;stlichen<LE/>
Ecke des Platzes. Auf der hohen Rampe<LE/>
des ansto&#xDF;enden <I>Jardin des Tuileries</I>, dort,<LE/>
von wo die Neugierigen immer zuschauen,<LE/>
wenn es Revolution in Paris gibt &#x2014; die<LE/>
Revolutionen beginnen und endigen <HYPH1 cont="meistens">mei-</HYPH1><LE/>
<HYPH2>stens</HYPH2> auf der <I>Place de la Concorde</I> &#x2014; dort<LE/>
stehen Tausende von Menschen, &#xFC;ber die</P>
</CELL></ROW></TABLE>
<FN>
<P parID="03468"><TAB/>* L. c., pag. 43.</P>
<P parID="03469"><TAB/>*** L. c., pag. 44.</P>
<P parID="03470"><TAB/>*** L. c., pag. 43.</P>
</FN>
<FT type="pn" num="280" c_text="&#x2014; 280 &#x2014;"/>
</PAGE>