<?xml version="1.0"?>
<?xml-stylesheet type="text/xsl" href="stand.xsl"?>
<PAGE xml:space="preserve">
<NAV_HEADER>
<PREV>WR-04-23_n0405.xml</PREV>
<NEXT>WR-04-23_n0407.xml</NEXT>
<UP></UP>
<DISP>Wiener Rundschau: Jg. 4, Nr. 23, S. 406</DISP>
<DOC_CHAR_NUM></DOC_CHAR_NUM>
<FOLDER_DOCS>552</FOLDER_DOCS>
<FOLDER_DOCS_RN></FOLDER_DOCS_RN>
<ISSUE_DOCS>20</ISSUE_DOCS>
<PUBL_DATE><PUBL_DAY></PUBL_DAY><PUBL_MONTH></PUBL_MONTH><PUBL_YEAR>1900</PUBL_YEAR></PUBL_DATE>
<NEXT_START/>
<TEXT_START/>
<ISSUE_PN></ISSUE_PN>
</NAV_HEADER>
<HD><CTEXT>SCHLAF: MULTATULI.</CTEXT></HD>
<TABLE parID="04629"><ROW ciID="0812"><CELL>
<P part="final" parID="04630"><HYPH2>lissa</HYPH2> weinte und ihre Tochter verlegen<LE/>
war, so steht offenbar alles, wovon er<LE/>
jetzt erz&#xE4;hlt hatte und was vor neunzehn<LE/>
Jahrhunderten geschehen ist, in einer <HYPH1 cont="gewissen">ge-</HYPH1><LE/>
<HYPH2>wissen</HYPH2> Beziehung zu der Gegenwart &#x2014;<LE/>
zu den beiden Frauen, und wahrscheinlich<LE/>
auch zu diesem verwilderten Dorfe, zu ihm<LE/>
selbst, zu allen Menschen. Wenn die Alte<LE/>
weinte, so war es nicht deshalb, weil er<LE/>
so r&#xFC;hrend erz&#xE4;hlen konnte, sondern weil<LE/>
Petrus ihr nahe war, und weil in ihrem<LE/>
ganzen Wesen ein mitf&#xFC;hlendes <HYPH1 cont="Verst&#xE4;ndnis">Verst&#xE4;nd-</HYPH1><LE/>
<HYPH2>nis</HYPH2> f&#xFC;r Das lebte, was mit Petrus <HYPH1 cont="vorgegegangen">vorge-</HYPH1><LE/>
<HYPH2>gegangen</HYPH2> war.</P>
<P part="initial" parID="04631"><TAB/>Und Freude &#xFC;berzog seine Seele. Er<LE/>
blieb einen Moment stehen, um Athem zu<LE/>
holen. &#xBB;Die Vergangenheit&#xAB;, dachte er,<LE/>
&#xBB;ist mit der Gegenwart durch eine <HYPH1 cont="ununterbrochene">un-</HYPH1><LE/>
<HYPH2>unterbrochene</HYPH2> Kette von Ereignissen <HYPH1 cont="verbunden">ver-</HYPH1><LE/>
<HYPH2>bunden</HYPH2>, die von einander ausgehen&#xAB;. Und<LE/>
es schien ihm, als h&#xE4;tte er soeben beide</P>
</CELL><CELL>
<P part="final" parID="04632">Enden der Kette gesehen: Er ber&#xFC;hrte ein<LE/>
Ende, und das zweite zitterte.</P>
<P parID="04633"><TAB/>Und als er mit der F&#xE4;hre den<LE/>
Fluss &#xFC;bersetzte, bergauf gieng und sein<LE/>
Heimatsdorf erblickte und den Westen,<LE/>
wo in einem schmalen Streifen die kalte<LE/>
Abendr&#xF6;the leuchtete, da dachte er daran,<LE/>
dass alles Wahre und Sch&#xF6;ne, welches<LE/>
dort, im Garten und Hof des Erzpriesters,<LE/>
die Menschenleben geleitet hat, sich <HYPH1 cont="ununterbrochen">un-</HYPH1><LE/>
<HYPH2>unterbrochen</HYPH2> bis zum heutigen Tag <HYPH1 cont="ausdehnt">aus-</HYPH1><LE/>
<HYPH2>dehnt</HYPH2> und im menschlichen Leben, auf<LE/>
Erden &#xFC;berhaupt, offenbar immer die<LE/>
Hauptsache bildete. Und ein Gef&#xFC;hl von<LE/>
Jugend, Gesundheit und Kraft &#x2014; er war<LE/>
erst zweiundzwanzig Jahre alt &#x2014; und<LE/>
eine unbeschreiblich s&#xFC;&#xDF;e Erwartung auf<LE/>
Gl&#xFC;ck, auf unbekanntes, geheimnisvolles<LE/>
Gl&#xFC;ck durchdrang ihn nach und nach.<LE/>
Und reizend, wunderbar und voll hohen<LE/>
Sinnes d&#xFC;nkte ihm das Leben.</P>
</CELL></ROW></TABLE>
<DIV_END divEndID="deID_2436_00858" startPtr="WR-04-23_n0404.xml#//DIV_START[@divStartID='dsID_2436_00859']"/>
<SEPARATOR num="8" type="undefined"/>
<DIV_START divStartID="dsID_2436_00860" endPtr="WR-04-23_n0411.xml#//DIV_END[@divEndID='deID_2436_00859']" titleID="tiID_2436_00227"/>
<TITLE titleID="tiID_2436_00227" parDivStartID="dsID_2436_00860"><TITLEPART type="main">MULTATULI.</TITLEPART><LE/>
<TITLEPART type="bystmt">Von <AUCTOR>JOHANNES SCHLAF</AUCTOR> (Berlin).</TITLEPART></TITLE>
<TABLE parID="04634"><ROW ciID="0813"><CELL>
<P part="initial" parID="04635"><TAB/><SPC>Multatuli</SPC> ist das gr&#xF6;&#xDF;te Genie und der<LE/>
bedeutendste Charakter, den die <HYPH1 cont="holl&#xE4;ndische">holl&#xE4;n-</HYPH1><LE/>
<HYPH2>dische</HYPH2> Literatur <DATERANGE>dieses Jahrhunderts</DATERANGE> <HYPH1 cont="hervorgebracht">her-</HYPH1><LE/>
<HYPH2>vorgebracht</HYPH2>. Und zwar ist er nicht so sehr<LE/>
Romandichter, Dramatiker, Lyriker und <HYPH1 cont="genialer">ge-</HYPH1><LE/>
<HYPH2>nialer</HYPH2> Feuilletonist, als vor allem <HYPH1 cont="Individualit&#xE4;t"><SPC>Indivi</SPC>-</HYPH1><LE/>
<HYPH2><SPC>dualit&#xE4;t</SPC></HYPH2>. In dem Sinne, wie heute etwa<LE/>
<SPC>Tolstoj</SPC> vor allem Pers&#xF6;nlichkeit ist, wie<LE/>
vielleicht <SPC>Ibsen</SPC> noch bedeutungsvoller als<LE/>
Pers&#xF6;nlichkeit denn als Philosoph, Lyriker<LE/>
und Wortk&#xFC;nstler erscheint; und wie diese,<LE/>
so ein <SPC>Maeterlinck</SPC> und mit ihnen noch so<LE/>
mancher andere. Es ist verst&#xE4;ndlich,<LE/>
was ich meine, und dass ich mit dem<LE/>
eben Ausgef&#xFC;hrten alles in dem Begriffe<LE/>
der Pers&#xF6;nlichkeit unterstreiche, was in ihr<LE/>
<SPC>Activit&#xE4;t</SPC>, und zwar ethische Activit&#xE4;t<LE/>
ist. Denn, obschon wir gerade in den<LE/>
letzten Jahrzehnten recht viel <HYPH1 cont="&#xE4;sthetisierten">&#xE4;stheti-</HYPH1><LE/>
<HYPH2>sierten</HYPH2> und auf neue, wohl gar bis daher<LE/>
unerh&#xF6;rte Kunstformen besonderen Wert<LE/>
legten, die Zeiten scheinen andere <HYPH1 cont="Bed&#xFC;rfnisse">Be-</HYPH1><LE/>
<HYPH2>d&#xFC;rfnisse</HYPH2> zu haben, als ein neues, gro&#xDF;es<LE/>
Kunstwerk hervorzubringen. Im &#xFC;brigen ist</P>
</CELL><CELL>
<P part="medial" parID="04636"><SPC>Pers&#xF6;nlichkeit</SPC> ja stets das Wesentliche<LE/>
und war es immer. Je nach den <HYPH1 cont="Zeitverh&#xE4;ltnissen">Zeit-</HYPH1><LE/>
<HYPH2>verh&#xE4;ltnissen</HYPH2> beth&#xE4;tigt sie sich <HYPH1 cont="k&#xFC;nstlerisch">k&#xFC;nst-</HYPH1><LE/>
<HYPH2>lerisch</HYPH2> oder in irgendeiner anderen Weise.<LE/>
Heute vielleicht nicht ohne Analogie zu<LE/>
den Zeiten des Ausgangs der Antike und<LE/>
der Geburt des Christenthums; heute, wo<LE/>
wir uns in dem Zeitalter einer ethischen<LE/>
&#xBB;Umwertung der Werte&#xAB; befinden, dr&#xE4;ngt<LE/>
sie vor allem wieder einmal nach ethischer<LE/>
Beth&#xE4;tigung; da die Presse aber gerade<LE/>
in unseren modernen Zeiten in bis daher<LE/>
unerh&#xF6;rter Weise Weltmacht ist, wird die<LE/>
Literatur und die Wortkunst der ethischen<LE/>
Pers&#xF6;nlichkeit zum vornehmsten Vehikel.<LE/>
Wie mancher unserer gro&#xDF;en neuzeitigen<LE/>
Romandichter oder Dramatiker w&#xFC;rde<LE/>
sonst vielleicht, wie dies in fr&#xFC;heren <HYPH1 cont="Jahrhunderten">Jahr-</HYPH1><LE/>
<HYPH2>hunderten</HYPH2> der Fall war, Wanderphilosoph<LE/>
sein! Und noch eins: Irgendwer hat im<LE/>
Laufe der letzten beiden Jahrzehnte <HYPH1 cont="gelegentlich">ge-</HYPH1><LE/>
<HYPH2>legentlich</HYPH2> einmal ausgesprochen, dass <HYPH1 cont="unsere">un-</HYPH1><LE/>
<HYPH2>sere</HYPH2> moderne Wortkunst im Zeichen des<LE/>
<SPC>Feuilletons</SPC> stehe und sich noch weit</P>
</CELL></ROW></TABLE>
<FT type="pn" num="406" c_text="&#x2014; 406 &#x2014;"/>
</PAGE>