<?xml version="1.0"?>
<?xml-stylesheet type="text/xsl" href="stand.xsl"?>
<PAGE xml:space="preserve">
<NAV_HEADER>
<PREV>WR-05-15_n0309.xml</PREV>
<NEXT>WR-05-15_n0311.xml</NEXT>
<UP></UP>
<DISP>Wiener Rundschau: Jg. 5, Nr. 15, S. 310</DISP>
<DOC_CHAR_NUM></DOC_CHAR_NUM>
<FOLDER_DOCS>360</FOLDER_DOCS>
<FOLDER_DOCS_RN></FOLDER_DOCS_RN>
<ISSUE_DOCS>18</ISSUE_DOCS>
<PUBL_DATE><PUBL_DAY>1</PUBL_DAY><PUBL_MONTH>8</PUBL_MONTH><PUBL_YEAR>1901</PUBL_YEAR></PUBL_DATE>
<NEXT_START/>
<TEXT_START/>
<ISSUE_PN></ISSUE_PN>
</NAV_HEADER>
<DIV_START divStartID="dsID_2436_01350" endPtr="WR-05-15_n0311.xml#//DIV_END[@divEndID='deID_2436_01352']"/>
<TITLE titleID="tiID_2436_00361"><TITLEPART type="repeated">RUNDSCHAU.</TITLEPART></TITLE>
<TABLE parID="07639"><ROW ciID="1223"><CELL>
<DIV_START divStartID="dsID_2436_01351" endPtr="WR-05-15_n0310.xml#//DIV_END[@divEndID='deID_2436_01349']"/>
<P parID="07640"><TAB/><SPC>Den Unterschied im Wesen des<LE/>
physiologischen und geometrischen<LE/>
Raumes</SPC> untersucht der Philosoph E. Mach<LE/>
im letzterschienenen <LANG iso="en">&#xBB;The Monist&#xAB;</LANG>. Der<LE/>
physiologische Raum ist begrenzt, niemals<LE/>
unendlich; das ihm correspondierende <HYPH1 cont="momentane">momen-</HYPH1><LE/>
<HYPH2>tane</HYPH2> Gesichtsfeld l&#xE4;sst viel eher auf den <HYPH1 cont="metageometrischen">meta-</HYPH1><LE/>
<HYPH2>geometrischen</HYPH2> Raum der modernen <HYPH1 cont="Mathematiker">Mathe-</HYPH1><LE/>
<HYPH2>matiker</HYPH2>, als den cubischen Raum des Euclid<LE/>
schlie&#xDF;en. Gewisse Eigenschaften sind dem<LE/>
physiologischen und dem geometrischen Raum<LE/>
gemeinsam: die Mannigfaltigkeit beider R&#xE4;ume<LE/>
ist dreidimensional; continuierliche Bewegung<LE/>
eines Punktes ist in beiden F&#xE4;llen ebenso wie<LE/>
die genaue Ortsdetermination m&#xF6;glich.</P>
<P parID="07641"><TAB/>Die Localisation von Reizen geh&#xF6;rt dem<LE/>
physiologischen Raum an &#x2014; die wechselseitige<LE/>
Anpassung verketteter Organe tritt in der<LE/>
Raumperception zutage. Die Gesammtheit der<LE/>
K&#xF6;rperoberfl&#xE4;che ist dem Tastsinn zug&#xE4;nglich,<LE/>
nur ein begrenzter Theil dem Gesichtssinn.<LE/>
Die Raumvorstellungen der einzelnen Sinne<LE/>
sind nicht identisch; der durch Empfindung<LE/>
entstandene Theil der Raumvorstellung <HYPH1 cont="repr&#xE4;sentiert">repr&#xE4;-</HYPH1><LE/>
<HYPH2>sentiert</HYPH2> ein System von Empfindungsgruppen.<LE/>
Obgleich der Gesichtssinn den klarsten und<LE/>
pr&#xE4;cisesten Charakter besitzt, ist der durch<LE/>
den Tastsinn gewonnene Raumeindruck <HYPH1 cont="biologisch">bio-</HYPH1><LE/>
<HYPH2>logisch</HYPH2> wertvoller. Auch dieser hat seine <HYPH1 cont="eigenth&#xFC;mlichen">eigen-</HYPH1><LE/>
<HYPH2>th&#xFC;mlichen</HYPH2> Abweichungen und <HYPH1 cont="Inhomogen&#xEB;it&#xE4;ten">Inhomoge-</HYPH1><LE/>
<HYPH2>n&#xEB;it&#xE4;ten</HYPH2> nach den drei Abmessungen wie der<LE/>
Gesichtsraum.</P>
<P parID="07642"><TAB/>&#xC4;nderungen in der Stetigkeit des Verlaufes<LE/>
der Reizeindr&#xFC;cke werden unmittelbar <HYPH1 cont="percipiert">per-</HYPH1><LE/>
<HYPH2>cipiert</HYPH2> (mithin auch die Abgeleiteten der <HYPH1 cont="Reizfunction">Reiz-</HYPH1><LE/>
<HYPH2>function</HYPH2>). Die Raumempfindung ist von der<LE/>
relativen Lage und Geschwindigkeit des <HYPH1 cont="Beobachters">Beob-</HYPH1><LE/>
<HYPH2>achters</HYPH2> zu den Au&#xDF;endingen abh&#xE4;ngig. <HYPH1 cont="Vollst&#xE4;ndige">Voll-</HYPH1><LE/>
<HYPH2>st&#xE4;ndige</HYPH2> Gewissheit kann nur bei &#xC1;usschluss<LE/>
aller Bewegung erzielt werden &#x2014; die <HYPH1 cont="geometrische">geome-</HYPH1><LE/>
<HYPH2>trische</HYPH2> Raumbetrachtung abstrahiert von dem<LE/>
Einflusse der relativen Bewegung und <HYPH1 cont="untersucht">unter-</HYPH1><LE/>
<HYPH2>sucht</HYPH2> blo&#xDF; die Lagenbeziehung der Objecte zu<LE/>
einander.</P>
<P parID="07643"><TAB/>Die empirische Raumanschauung bildet<LE/>
ein entwicklungsgeschichtliches Problem &#x2014; sie<LE/>
ist das Resultat der specifischen Raumeindr&#xFC;cke<LE/>
concurrierender Sinnesgebiete. Das Verdienst<LE/>
<SPC>Kants</SPC> ist die Problemstellung. <AUCTOR>&#x3B2;</AUCTOR></P>
<DIV_END divEndID="deID_2436_01349" startPtr="WR-05-15_n0310.xml#//DIV_START[@divStartID='dsID_2436_01351']"/>
<SEPARATOR type="asterisk"/>
<DIV_START divStartID="dsID_2436_01352" endPtr="WR-05-15_n0310.xml#//DIV_END[@divEndID='deID_2436_01350']"/>
<P part="initial" parID="07644"><TAB/><SPC>Eine Consequenz aus der Lehre<LE/>
vom psychophysischen Parallelismus</SPC><LE/>
gibt Dr. J. Pikler im letzten Heft der <SPC><HYPH1 cont="Zeitschrift">Zeit-</HYPH1><LE/>
<HYPH2>schrift</HYPH2> f&#xFC;r Psychologie und <HYPH1 cont="Physiologie">Physio-</HYPH1><LE/>
<HYPH2>logie</HYPH2> der Sinnesorgane</SPC>. Von der Materie<LE/>
wird nur ihre Ver&#xE4;nderung wahrgenommen;<LE/>
da die Bewegung nur dadurch besteht, dass<LE/>
der gewesene Bewegungszustand im <HYPH1 cont="gegenw&#xE4;rtigen">gegen-</HYPH1><LE/>
<HYPH2>w&#xE4;rtigen</HYPH2> potentiell fest existiert, so besteht<LE/>
auch im Bewusstsein die Summe aller <HYPH1 cont="vorhergegangenen">vorher-</HYPH1><LE/>
<HYPH2>gegangenen</HYPH2> Bewusstseinsver&#xE4;nderungen <SPC><HYPH1 cont="potentiell">poten-</HYPH1><LE/>
<HYPH2>tiell</HYPH2></SPC> fort. Die materiellen Theilchen bewegen</P>
</CELL><CELL>
<P part="final" parID="07645">sich, insoferne sie Object sind, sie <SPC>haben ein<LE/>
Ged&#xE4;chtnis</SPC>, insoferne sie Subject sind. <HYPH1 cont="Hieraus">Hier-</HYPH1><LE/>
<HYPH2>aus</HYPH2> w&#xFC;rde sich ergeben, dass die Tr&#xE4;ger der<LE/>
einzelnen specifischen Sinnesenergien das <HYPH1 cont="Ged&#xE4;chtnis">Ge-</HYPH1><LE/>
<HYPH2>d&#xE4;chtnis</HYPH2> ihrer eigenen Wirksamkeit besitzen;<LE/>
jedoch steht im Widerspruch mit dieser <HYPH1 cont="Anschauung">An-</HYPH1><LE/>
<HYPH2>schauung</HYPH2> die Thatsachc des Bleibens der <HYPH1 cont="Zusammensetzung">Zu-</HYPH1><LE/>
<HYPH2>sammensetzung</HYPH2> der Organismen trotz des <HYPH1 cont="Stoffwechsels">Stoff-</HYPH1><LE/>
<HYPH2>wechsels</HYPH2>. Der neu assimilierte Stoff gewinnt<LE/>
n&#xE4;mlich dieselben Bewegungen wie der fr&#xFC;here,<LE/>
daher ist die vorher angef&#xFC;hrte Definition zu<LE/>
erweitern: &#xBB;Die einander folgenden, <HYPH1 cont="verschiedensten">verschie-</HYPH1><LE/>
<HYPH2>densten</HYPH2> Bewusstseinszust&#xE4;nde &#x2014; z. B. <HYPH1 cont="Empfindungen">Empfin-</HYPH1><LE/>
<HYPH2>dungen</HYPH2> verschiedener Sinne &#x2014; desselben <HYPH1 cont="Individuums">In-</HYPH1><LE/>
<HYPH2>dividuums</HYPH2> haben ihr physisches Correlat in<LE/>
weiteren Ver&#xE4;nderungen derselben Bewegungen<LE/>
oder Bewegungs&#xE4;nderungen, welche die <HYPH1 cont="physischen">phy-</HYPH1><LE/>
<HYPH2>sischen</HYPH2> Correlate der fr&#xFC;heren <HYPH1 cont="Bewusstseinszust&#xE4;nde">Bewusstseins-</HYPH1><LE/>
<HYPH2>zust&#xE4;nde</HYPH2> waren und deren &#xDC;berbleibsel die<LE/>
Correlate des Ged&#xE4;chtnisses dieser <HYPH1 cont="Bewusstseinszust&#xE4;nde">Bewusstseins-</HYPH1><LE/>
<HYPH2>zust&#xE4;nde</HYPH2> sind. Dem einheitlichen <HYPH1 cont="Bewusstseinsverlauf">Bewusstseins-</HYPH1><LE/>
<HYPH2>verlauf</HYPH2> desselben Individuums entsprechen<LE/>
nicht einander folgende Ver&#xE4;nderungen <HYPH1 cont="verschiedener">ver-</HYPH1><LE/>
<HYPH2>schiedener</HYPH2> Stellen der nerv&#xF6;sen Centralmasse,<LE/>
sondern <SPC>Ver&#xE4;nderungen von <HYPH1 cont="Ver&#xE4;nderungen">Ver&#xE4;nder-</HYPH1><LE/>
<HYPH2>ungen</HYPH2> in denselben Stellen</SPC>.&#xAB; <AUCTOR><I>w.</I></AUCTOR></P>
<DIV_END divEndID="deID_2436_01350" startPtr="WR-05-15_n0310.xml#//DIV_START[@divStartID='dsID_2436_01352']"/>
<SEPARATOR type="asterisk"/>
<DIV_START divStartID="dsID_2436_01353" endPtr="WR-05-15_n0311.xml#//DIV_END[@divEndID='deID_2436_01351']"/>
<P parID="07646"><TAB/><SPC>Kants Bedeutung f&#xFC;r die <HYPH1 cont="Musik-&#xC4;sthetik">Musik-</HYPH1><LE/>
<HYPH2>&#xC4;sthetik</HYPH2></SPC> behandelt mit viel Sachkenntnis<LE/>
Franz Marschner in den letzten &#xBB;<SPC><HYPH1 cont="Kant-Studien">Kant-Stu-</HYPH1><LE/>
<HYPH2>dien</HYPH2></SPC>&#xAB;. In der &#xBB;Kritik der Urtheilskraft&#xAB; finden<LE/>
sich bereits die Pole der heutigen <HYPH1 cont="Musikbetrachtung">Musik-</HYPH1><LE/>
<HYPH2>betrachtung</HYPH2>: Formal- und Inhalts-&#xC4;sthetik als<LE/>
Ausgangspunkt der Kritik. Die Musik nimmt<LE/>
bei Kant eine tiefe Stellung ein: Das Tonspiel<LE/>
ist blo&#xDF; ein Wechsel von Empfindungen. Das<LE/>
Spiel eilt in der Musik von der k&#xF6;rperlichen<LE/>
Empfindung zu den &#xE4;sthetischen Ideen, von<LE/>
hier (mit vereinter Kraft) auf den K&#xF6;rper<LE/>
(&#xBB;Kritik der Urtheilskraft&#xAB;, &#xA7; 54).</P>
<P part="initial" parID="07647"><TAB/>Diese formal-&#xE4;sthetische Gedankenreihe<LE/>
wird von <SPC>Hanslick</SPC> aufgenommen und <HYPH1 cont="weitergef&#xFC;hrt">weiter-</HYPH1><LE/>
<HYPH2>gef&#xFC;hrt</HYPH2> (&#xBB;Vom Musikalisch-Sch&#xF6;nen&#xAB;). Das<LE/>
Sch&#xF6;ne hat an sich selbst &#xFC;berhaupt keinen<LE/>
Zweck. Nicht das (vitale) Gef&#xFC;hl, sondern die<LE/>
Phantasie ist Organ der Reception des Sch&#xF6;nen.<LE/>
Affecte k&#xF6;nnen durch die Musik nicht erregt<LE/>
werden. Tonwerk und Stimmung h&#xE4;ngen nicht<LE/>
zusammen. Gegenstand der Musik sind einzig und<LE/>
allein t&#xF6;nend bewegte Formen. Die Tonkunst<LE/>
ist inhaltslos. &#x2014; Die Bedeutung dieser Gedanken<LE/>
liegt zun&#xE4;chst darin, dass die durchaus <HYPH1 cont="unhaltbare">unhalt-</HYPH1><LE/>
<HYPH2>bare</HYPH2> &#xBB;Gef&#xFC;hls-&#xC4;sthetik&#xAB; durch die Hanslick&#x2019;sche<LE/>
Schrift ihr Ende fand. <SPC>Lotze</SPC> findet (<DATE>1855</DATE>) in<LE/>
seiner Kritik der Hanslick&#x2019;schen Studie, dass<LE/>
Hanslick im Kampfe gegen pathologische<LE/>
Gef&#xFC;hlseindr&#xFC;cke zu weit gegangen, dass es<LE/>
jedoch richtig sei, nur das Dynamische als<LE/>
unmittelbaren Inhalt der Musik zu bezeichnen.<LE/>
Die Musik &#xFC;bertr&#xE4;gt auf ihre Figuren den<LE/>
Gef&#xFC;hlswert, der f&#xFC;r uns den Inhalt hat, an</P>
</CELL></ROW></TABLE>
<FT type="pn" num="310" c_text="&#x2014; 310 &#x2014;"/>
</PAGE>